<?xml version='1.0' encoding='utf-8'?>
<NamePresets>
  <NamePreset>
    <Sex>Female</Sex>
    <GivenNames>
      <Name>菜野花</Name>
    </GivenNames>
    <FamilyNames>
      <Name>相沢</Name>
    </FamilyNames>
    <Translations>
      <Translation>
        <GivenName>Nanoka</GivenName>
        <FamilyName>Aizawa</FamilyName>
      </Translation>
    </Translations>
  </NamePreset>
  <NamePreset>
    <Sex>Female</Sex>
    <GivenNames>
      <Name>歩</Name>
    </GivenNames>
    <FamilyNames>
      <Name>速志</Name>
    </FamilyNames>
    <Translations>
      <Translation>
        <GivenName>Ayumi</GivenName>
        <FamilyName>Hayashi</FamilyName>
      </Translation>
    </Translations>
  </NamePreset>
  <NamePreset>
    <Sex>Female</Sex>
    <GivenNames>
      <Name>藍里</Name>
    </GivenNames>
    <FamilyNames>
      <Name>林田</Name>
    </FamilyNames>
    <Translations>
      <Translation>
        <GivenName>Airi</GivenName>
        <FamilyName>Hayashida</FamilyName>
      </Translation>
    </Translations>
  </NamePreset>
  <NamePreset>
    <Sex>Female</Sex>
    <GivenNames>
      <Name>由香里</Name>
    </GivenNames>
    <FamilyNames>
      <Name>廣澤</Name>
    </FamilyNames>
    <Translations>
      <Translation>
        <GivenName>Yukari</GivenName>
        <FamilyName>Hirosawa</FamilyName>
      </Translation>
    </Translations>
  </NamePreset>
  <NamePreset>
    <Sex>Female</Sex>
    <GivenNames>
      <Name>菜々美</Name>
    </GivenNames>
    <FamilyNames>
      <Name>久海</Name>
    </FamilyNames>
    <Translations>
      <Translation>
        <GivenName>Nanami</GivenName>
        <FamilyName>Hisami</FamilyName>
      </Translation>
    </Translations>
  </NamePreset>
  <NamePreset>
    <Sex>Female</Sex>
    <GivenNames>
      <Name>志保</Name>
    </GivenNames>
    <FamilyNames>
      <Name>岩崎</Name>
    </FamilyNames>
    <Translations>
      <Translation>
        <GivenName>Shiho</GivenName>
        <FamilyName>Iwasaki</FamilyName>
      </Translation>
    </Translations>
  </NamePreset>
  <NamePreset>
    <Sex>Female</Sex>
    <GivenNames>
      <Name>実波</Name>
    </GivenNames>
    <FamilyNames>
      <Name>片山</Name>
    </FamilyNames>
    <Translations>
      <Translation>
        <GivenName>Minami</GivenName>
        <FamilyName>Katayama</FamilyName>
      </Translation>
    </Translations>
  </NamePreset>
  <NamePreset>
    <Sex>Female</Sex>
    <GivenNames>
      <Name>夏夜</Name>
    </GivenNames>
    <FamilyNames>
      <Name>菊間</Name>
    </FamilyNames>
    <Translations>
      <Translation>
        <GivenName>Kaya</GivenName>
        <FamilyName>Kikuma</FamilyName>
      </Translation>
    </Translations>
  </NamePreset>
  <NamePreset>
    <Sex>Female</Sex>
    <GivenNames>
      <Name>ティナ</Name>
    </GivenNames>
    <FamilyNames>
      <Name>小早川</Name>
    </FamilyNames>
    <Translations>
      <Translation>
        <GivenName>Tina</GivenName>
        <FamilyName>Kobayakawa</FamilyName>
      </Translation>
    </Translations>
  </NamePreset>
  <NamePreset>
    <Sex>Female</Sex>
    <GivenNames>
      <Name>麻衣</Name>
    </GivenNames>
    <FamilyNames>
      <Name>近藤</Name>
    </FamilyNames>
    <Translations>
      <Translation>
        <GivenName>Mai</GivenName>
        <FamilyName>Kondo</FamilyName>
      </Translation>
    </Translations>
  </NamePreset>
  <NamePreset>
    <Sex>Female</Sex>
    <GivenNames>
      <Name>音芽</Name>
    </GivenNames>
    <FamilyNames>
      <Name>守島</Name>
    </FamilyNames>
    <Translations>
      <Translation>
        <GivenName>Otome</GivenName>
        <FamilyName>Morishima</FamilyName>
      </Translation>
    </Translations>
  </NamePreset>
  <NamePreset>
    <Sex>Female</Sex>
    <GivenNames>
      <Name>佳乃</Name>
    </GivenNames>
    <FamilyNames>
      <Name>七瀬</Name>
    </FamilyNames>
    <Translations>
      <Translation>
        <GivenName>Yoshino</GivenName>
        <FamilyName>Nanase</FamilyName>
      </Translation>
    </Translations>
  </NamePreset>
  <NamePreset>
    <Sex>Female</Sex>
    <GivenNames>
      <Name>仁美</Name>
    </GivenNames>
    <FamilyNames>
      <Name>二宮</Name>
    </FamilyNames>
    <Translations>
      <Translation>
        <GivenName>Hitomi</GivenName>
        <FamilyName>Ninomiya</FamilyName>
      </Translation>
    </Translations>
  </NamePreset>
  <NamePreset>
    <Sex>Female</Sex>
    <GivenNames>
      <Name>陽菜</Name>
    </GivenNames>
    <FamilyNames>
      <Name>大石</Name>
    </FamilyNames>
    <Translations>
      <Translation>
        <GivenName>Hina</GivenName>
        <FamilyName>Ohishi</FamilyName>
      </Translation>
    </Translations>
  </NamePreset>
  <NamePreset>
    <Sex>Female</Sex>
    <GivenNames>
      <Name>未夕</Name>
    </GivenNames>
    <FamilyNames>
      <Name>岡本</Name>
    </FamilyNames>
    <Translations>
      <Translation>
        <GivenName>Miyu</GivenName>
        <FamilyName>Okamoto</FamilyName>
      </Translation>
    </Translations>
  </NamePreset>
  <NamePreset>
    <Sex>Female</Sex>
    <GivenNames>
      <Name>千明</Name>
    </GivenNames>
    <FamilyNames>
      <Name>桜井</Name>
    </FamilyNames>
    <Translations>
      <Translation>
        <GivenName>Chiaki</GivenName>
        <FamilyName>Sakurai</FamilyName>
      </Translation>
    </Translations>
  </NamePreset>
  <NamePreset>
    <Sex>Female</Sex>
    <GivenNames>
      <Name>真夢</Name>
    </GivenNames>
    <FamilyNames>
      <Name>島田</Name>
    </FamilyNames>
    <Translations>
      <Translation>
        <GivenName>Mayu</GivenName>
        <FamilyName>Shimada</FamilyName>
      </Translation>
    </Translations>
  </NamePreset>
  <NamePreset>
    <Sex>Female</Sex>
    <GivenNames>
      <Name>美桜</Name>
    </GivenNames>
    <FamilyNames>
      <Name>白川</Name>
    </FamilyNames>
    <Translations>
      <Translation>
        <GivenName>Mio</GivenName>
        <FamilyName>Shirakawa</FamilyName>
      </Translation>
    </Translations>
  </NamePreset>
  <NamePreset>
    <Sex>Female</Sex>
    <GivenNames>
      <Name>茉莉花</Name>
    </GivenNames>
    <FamilyNames>
      <Name>杉原</Name>
    </FamilyNames>
    <Translations>
      <Translation>
        <GivenName>Marika</GivenName>
        <FamilyName>Sugihara</FamilyName>
      </Translation>
    </Translations>
  </NamePreset>
  <NamePreset>
    <Sex>Female</Sex>
    <GivenNames>
      <Name>さくら</Name>
    </GivenNames>
    <FamilyNames>
      <Name>杉原</Name>
    </FamilyNames>
    <Translations>
      <Translation>
        <GivenName>Sakura</GivenName>
        <FamilyName>Sugihara</FamilyName>
      </Translation>
    </Translations>
  </NamePreset>
  <NamePreset>
    <Sex>Female</Sex>
    <GivenNames>
      <Name>萌歌</Name>
    </GivenNames>
    <FamilyNames>
      <Name>鈴木</Name>
    </FamilyNames>
    <Translations>
      <Translation>
        <GivenName>Moka</GivenName>
        <FamilyName>Suzuki</FamilyName>
      </Translation>
    </Translations>
  </NamePreset>
  <NamePreset>
    <Sex>Female</Sex>
    <GivenNames>
      <Name>玲奈</Name>
    </GivenNames>
    <FamilyNames>
      <Name>鈴木</Name>
    </FamilyNames>
    <Translations>
      <Translation>
        <GivenName>Rena</GivenName>
        <FamilyName>Suzuki</FamilyName>
      </Translation>
    </Translations>
  </NamePreset>
  <NamePreset>
    <Sex>Female</Sex>
    <GivenNames>
      <Name>里佳</Name>
    </GivenNames>
    <FamilyNames>
      <Name>高科</Name>
    </FamilyNames>
    <Translations>
      <Translation>
        <GivenName>Rika</GivenName>
        <FamilyName>Takashina</FamilyName>
      </Translation>
    </Translations>
  </NamePreset>
  <NamePreset>
    <Sex>Female</Sex>
    <GivenNames>
      <Name>順子</Name>
    </GivenNames>
    <FamilyNames>
      <Name>丹下</Name>
    </FamilyNames>
    <Translations>
      <Translation>
        <GivenName>Junko</GivenName>
        <FamilyName>Tange</FamilyName>
      </Translation>
    </Translations>
  </NamePreset>
  <NamePreset>
    <Sex>Female</Sex>
    <GivenNames>
      <Name>マキナＸ</Name>
    </GivenNames>
    <FamilyNames/>
    <Translations>
      <Translation>
        <GivenName>Makina-X</GivenName>
      </Translation>
    </Translations>
  </NamePreset>
  <NamePreset>
    <Sex>Female</Sex>
    <GivenNames>
      <Name>Ｘ</Name>
    </GivenNames>
    <FamilyNames>
      <Name>マキナ</Name>
    </FamilyNames>
    <Translations>
      <Translation>
        <GivenName>X</GivenName>
        <FamilyName>Makina</FamilyName>
      </Translation>
    </Translations>
  </NamePreset>
  <NamePreset>
    <Sex>Female</Sex>
    <GivenNames>
      <Name>涼華</Name>
    </GivenNames>
    <FamilyNames>
      <Name>八神</Name>
    </FamilyNames>
    <Translations>
      <Translation>
        <GivenName>Suzuka</GivenName>
        <FamilyName>Yagami</FamilyName>
      </Translation>
    </Translations>
  </NamePreset>
  <NamePreset>
    <Sex>Female</Sex>
    <GivenNames>
      <Name>愛</Name>
    </GivenNames>
    <FamilyNames>
      <Name>吉川</Name>
    </FamilyNames>
    <Translations>
      <Translation>
        <GivenName>Megumi</GivenName>
        <FamilyName>Yoshikawa</FamilyName>
      </Translation>
    </Translations>
  </NamePreset>
  <NamePreset>
    <Sex>Female</Sex>
    <GivenNames>
      <Name>栞</Name>
    </GivenNames>
    <FamilyNames>
      <Name>柚沢</Name>
    </FamilyNames>
    <Translations>
      <Translation>
        <GivenName>Shiori</GivenName>
        <FamilyName>Yuzusawa</FamilyName>
      </Translation>
    </Translations>
  </NamePreset>
  <NamePreset>
    <Sex>Male</Sex>
    <GivenNames>
      <Name>相</Name>
    </GivenNames>
    <FamilyNames>
      <Name>早坂</Name>
    </FamilyNames>
    <Translations>
      <Translation>
        <GivenName>Tasuku</GivenName>
        <FamilyName>Hayasaka</FamilyName>
      </Translation>
    </Translations>
  </NamePreset>
  <NamePreset>
    <Sex>Male</Sex>
    <GivenNames>
      <Name>耕平</Name>
    </GivenNames>
    <FamilyNames>
      <Name>松田</Name>
    </FamilyNames>
    <Translations>
      <Translation>
        <GivenName>Kouhei</GivenName>
        <FamilyName>Matsuda</FamilyName>
      </Translation>
    </Translations>
  </NamePreset>
  <NamePreset>
    <Sex>Male</Sex>
    <GivenNames>
      <Name>徹</Name>
    </GivenNames>
    <FamilyNames>
      <Name>白木</Name>
    </FamilyNames>
    <Translations>
      <Translation>
        <GivenName>Toru</GivenName>
        <FamilyName>Shiraki</FamilyName>
      </Translation>
    </Translations>
  </NamePreset>
</NamePresets>
